protontherapy/__init__.py
protontherapy/protontherapy.py
protontherapy-0.1.0.dist-info/METADATA
protontherapy-0.1.0.dist-info/WHEEL
protontherapy-0.1.0.dist-info/RECORD
